basalt/__init__.py
basalt/_version.py
basalt/client.py
basalt/config.py
basalt/_internal/__init__.py
basalt/_internal/base_client.py
basalt/_internal/http.py
basalt/datasets/__init__.py
basalt/datasets/client.py
basalt/datasets/file_upload.py
basalt/datasets/models.py
basalt/experiments/__init__.py
basalt/experiments/client.py
basalt/experiments/models.py
basalt/observability/__init__.py
basalt/observability/api.py
basalt/observability/config.py
basalt/observability/context_managers.py
basalt/observability/decorators.py
basalt/observability/evaluators.py
basalt/observability/instrumentation.py
basalt/observability/processors.py
basalt/observability/request_tracing.py
basalt/observability/resilient_exporters.py
basalt/observability/semconv.py
basalt/observability/spans.py
basalt/observability/trace.py
basalt/observability/trace_context.py
basalt/observability/types.py
basalt/observability/utils.py
basalt/prompts/__init__.py
basalt/prompts/client.py
basalt/prompts/models.py
basalt/types/__init__.py
basalt/types/cache.py
basalt/types/common.py
basalt/types/exceptions.py
basalt/utils/__init__.py
basalt/utils/memcache.py
basalt_sdk-1.1.1.dist-info/METADATA
basalt_sdk-1.1.1.dist-info/WHEEL
basalt_sdk-1.1.1.dist-info/RECORD
