Metadata-Version: 2.4
Name: basalt_sdk
Version: 1.1.1
Summary: Basalt SDK for python
Project-URL: Homepage, https://github.com/basalt-ai/basalt-python
Author-email: Basalt <support@getbasalt.ai>
License-Expression: MIT
Keywords: ai,basalt,python,sdk
Classifier: Operating System :: OS Independent
Classifier: Programming Language :: Python :: 3
Requires-Python: >=3.10
Requires-Dist: black>=26.1.0
Requires-Dist: httpx>=0.28.1
Requires-Dist: jinja2>=3.1.6
Requires-Dist: opentelemetry-api~=1.39.1
Requires-Dist: opentelemetry-exporter-otlp~=1.39.1
Requires-Dist: opentelemetry-instrumentation-httpx~=0.59b0
Requires-Dist: opentelemetry-instrumentation~=0.59b0
Requires-Dist: opentelemetry-sdk~=1.39.1
Requires-Dist: opentelemetry-semantic-conventions~=0.59b0
Requires-Dist: typing-extensions>=4.10.0
Requires-Dist: wrapt~=1.17.3
Provides-Extra: all
Requires-Dist: opentelemetry-instrumentation-anthropic~=0.51.0; extra == 'all'
Requires-Dist: opentelemetry-instrumentation-bedrock~=0.51.0; extra == 'all'
Requires-Dist: opentelemetry-instrumentation-chromadb~=0.51.0; extra == 'all'
Requires-Dist: opentelemetry-instrumentation-google-generativeai~=0.51.0; extra == 'all'
Requires-Dist: opentelemetry-instrumentation-langchain~=0.51.0; extra == 'all'
Requires-Dist: opentelemetry-instrumentation-llamaindex~=0.51.0; extra == 'all'
Requires-Dist: opentelemetry-instrumentation-mistralai~=0.51.0; extra == 'all'
Requires-Dist: opentelemetry-instrumentation-openai~=0.51.0; extra == 'all'
Requires-Dist: opentelemetry-instrumentation-pinecone~=0.51.0; extra == 'all'
Requires-Dist: opentelemetry-instrumentation-qdrant~=0.51.0; extra == 'all'
Requires-Dist: opentelemetry-instrumentation-vertexai~=0.51.0; extra == 'all'
Provides-Extra: anthropic
Requires-Dist: opentelemetry-instrumentation-anthropic~=0.51.0; extra == 'anthropic'
Provides-Extra: bedrock
Requires-Dist: opentelemetry-instrumentation-bedrock~=0.51.0; extra == 'bedrock'
Provides-Extra: chromadb
Requires-Dist: opentelemetry-instrumentation-chromadb~=0.51.0; extra == 'chromadb'
Provides-Extra: dev
Requires-Dist: anthropic; extra == 'dev'
Requires-Dist: coverage; extra == 'dev'
Requires-Dist: google-genai; extra == 'dev'
Requires-Dist: mistralai; extra == 'dev'
Requires-Dist: openai; extra == 'dev'
Requires-Dist: opentelemetry-instrumentation-anthropic; extra == 'dev'
Requires-Dist: opentelemetry-instrumentation-google-genai; extra == 'dev'
Requires-Dist: opentelemetry-instrumentation-google-generativeai; extra == 'dev'
Requires-Dist: opentelemetry-instrumentation-openai; extra == 'dev'
Requires-Dist: opentelemetry-instrumentation-vertexai; extra == 'dev'
Requires-Dist: parameterized; extra == 'dev'
Requires-Dist: pytest; extra == 'dev'
Requires-Dist: pytest-asyncio; extra == 'dev'
Requires-Dist: pytest-cov; extra == 'dev'
Requires-Dist: requests; extra == 'dev'
Requires-Dist: ruff; extra == 'dev'
Requires-Dist: setuptools; extra == 'dev'
Requires-Dist: twine; extra == 'dev'
Requires-Dist: wheel; extra == 'dev'
Provides-Extra: framework-all
Requires-Dist: opentelemetry-instrumentation-langchain~=0.51.0; extra == 'framework-all'
Requires-Dist: opentelemetry-instrumentation-llamaindex~=0.51.0; extra == 'framework-all'
Provides-Extra: google-generativeai
Requires-Dist: opentelemetry-instrumentation-google-generativeai~=0.51.0; extra == 'google-generativeai'
Provides-Extra: langchain
Requires-Dist: opentelemetry-instrumentation-langchain~=0.51.0; extra == 'langchain'
Provides-Extra: llamaindex
Requires-Dist: opentelemetry-instrumentation-llamaindex~=0.51.0; extra == 'llamaindex'
Provides-Extra: llm-all
Requires-Dist: opentelemetry-instrumentation-anthropic~=0.51.0; extra == 'llm-all'
Requires-Dist: opentelemetry-instrumentation-bedrock~=0.51.0; extra == 'llm-all'
Requires-Dist: opentelemetry-instrumentation-google-generativeai~=0.51.0; extra == 'llm-all'
Requires-Dist: opentelemetry-instrumentation-mistralai~=0.51.0; extra == 'llm-all'
Requires-Dist: opentelemetry-instrumentation-openai~=0.51.0; extra == 'llm-all'
Requires-Dist: opentelemetry-instrumentation-vertexai~=0.51.0; extra == 'llm-all'
Provides-Extra: mistralai
Requires-Dist: opentelemetry-instrumentation-mistralai~=0.51.0; extra == 'mistralai'
Provides-Extra: openai
Requires-Dist: opentelemetry-instrumentation-openai~=0.51.0; extra == 'openai'
Provides-Extra: pinecone
Requires-Dist: opentelemetry-instrumentation-pinecone~=0.51.0; extra == 'pinecone'
Provides-Extra: qdrant
Requires-Dist: opentelemetry-instrumentation-qdrant~=0.51.0; extra == 'qdrant'
Provides-Extra: vector-all
Requires-Dist: opentelemetry-instrumentation-chromadb~=0.51.0; extra == 'vector-all'
Requires-Dist: opentelemetry-instrumentation-pinecone~=0.51.0; extra == 'vector-all'
Requires-Dist: opentelemetry-instrumentation-qdrant~=0.51.0; extra == 'vector-all'
Provides-Extra: vertex-ai
Requires-Dist: opentelemetry-instrumentation-vertexai~=0.51.0; extra == 'vertex-ai'
